{
  "kind": "collectionType",
  "collectionName": "comments",
  "info": {
    "singularName": "comment",
    "pluralName": "comments",
    "displayName": "Comment"
  },
  "options": {
    "draftAndPublish": true
  },
  "pluginOptions": {},
  "attributes": {
    "Content": {
      "type": "text"
    },
    
    "parent": {
      "type": "relation",
      "relation": "manyToOne",
      "target": "api::comment.comment",
      "inversedBy": "replies"
    },
    "likes": {
      "type": "json"
    },
    "replies": {
      "type": "relation",
      "relation": "oneToMany",
      "target": "api::comment.comment",
      "mappedBy": "parent"
    },
    "article": {
      "type": "relation",
      "relation": "manyToOne",
      "target": "api::article.article",
      "inversedBy": "comments"
    },
    "dislikes": {
      "type": "json"
    },
    "user": {
      "type": "relation",
      "relation": "manyToOne",
      "target": "plugin::users-permissions.user",
      "inversedBy": "comments"
    },
    "repliesCount": {
      "type": "integer",
      "default": 0
    }
  }
}
